circleci-stubs/__init__.pyi
circleci-stubs/api.pyi
circleci-stubs/error.pyi
circleci-stubs/experimental.pyi
circleci-stubs/sdk.pyi
circleci-stubs/version.pyi
circleci_stubs-0.1.3.dist-info/LICENSE
circleci_stubs-0.1.3.dist-info/METADATA
circleci_stubs-0.1.3.dist-info/WHEEL
circleci_stubs-0.1.3.dist-info/top_level.txt
circleci_stubs-0.1.3.dist-info/RECORD
