Metadata-Version: 2.1
Name: circleci-stubs
Version: 0.1.3
Summary: Typing stubs for CircleCI
Classifier: Intended Audience :: Developers
Classifier: Programming Language :: Python
License-File: LICENSE
Requires-Dist: circleci
Provides-Extra: dev
Requires-Dist: mypy ; extra == 'dev'
Requires-Dist: setuptools ; extra == 'dev'
Requires-Dist: wheel ; extra == 'dev'
